{
  "solicitacao": [
    {
      "insumo": "{\"ItemCode\":\"022592\",\"ItemName\":\"ABACUS HC\",\"ItmsGrpNam\":\"FUNGICIDAS\",\"InvntryUom\":\"LITRO\",\"OnHand\":\"1.743,00\",\"WhsCode\":\"03.MATR\"}",
      "quantidade": 100
    }
  ],
  "unidade": "apples",
  "safra": "oranges",
  "n_safras": [
    {
      "value": "apples",
      "label": "Apples"
    },
    {
      "value": "oranges",
      "label": "Oranges"
    },
    {
      "value": "bananas",
      "label": "Bananas"
    }
  ],
  "n_filiais": [
    {
      "value": "apples",
      "label": "Apples"
    },
    {
      "value": "oranges",
      "label": "Oranges"
    },
    {
      "value": "bananas",
      "label": "Bananas"
    }
  ]
}