{
  "ui:layout": [
    {
      "BPLId": {},
      "WhsCode": {
        "sm": 2,
        "md": 2,
        "lg": 4
      }
    },
    {
      "idFarmbox": {},
      "novoIdFarmbox": {}
    },
    {
      "idFarmbox": {},
      "idSolinftec": {}
    }
  ],
  "idFarmbox": {
    "ui:autofocus": true,
    "ui:emptyValue": "",
    "ui:description": "Informe o ID do depósito no Farmbox"
  },
  "idSolinftec": {
    "ui:autofocus": true,
    "ui:emptyValue": "",
    "ui:description": "Informe o ID do depósito no Solinftec"
  },
  "BPLId": {
    "ui:disabled": {}
  },
  "WhsCode": {
    "ui:disabled": {}
  }
}